qgym/__init__.py
qgym/custom_types.py
qgym/py.typed
qgym/envs/__init__.py
qgym/envs/initial_mapping/__init__.py
qgym/envs/initial_mapping/initial_mapping.py
qgym/envs/initial_mapping/initial_mapping_rewarders.py
qgym/envs/initial_mapping/initial_mapping_state.py
qgym/envs/initial_mapping/initial_mapping_visualiser.py
qgym/envs/routing/__init__.py
qgym/envs/routing/routing.py
qgym/envs/routing/routing_rewarders.py
qgym/envs/routing/routing_state.py
qgym/envs/routing/routing_visualiser.py
qgym/envs/scheduling/__init__.py
qgym/envs/scheduling/machine_properties.py
qgym/envs/scheduling/rulebook.py
qgym/envs/scheduling/scheduling.py
qgym/envs/scheduling/scheduling_dataclasses.py
qgym/envs/scheduling/scheduling_rewarders.py
qgym/envs/scheduling/scheduling_state.py
qgym/envs/scheduling/scheduling_visualiser.py
qgym/generators/__init__.py
qgym/generators/circuit.py
qgym/generators/graph.py
qgym/generators/interaction.py
qgym/spaces/__init__.py
qgym/spaces/box.py
qgym/spaces/dict.py
qgym/spaces/discrete.py
qgym/spaces/multi_binary.py
qgym/spaces/multi_discrete.py
qgym/templates/__init__.py
qgym/templates/environment.py
qgym/templates/rewarder.py
qgym/templates/state.py
qgym/templates/visualiser.py
qgym/utils/__init__.py
qgym/utils/gate_encoder.py
qgym/utils/input_parsing.py
qgym/utils/input_validation.py
qgym/utils/visualisation/__init__.py
qgym/utils/visualisation/colors.py
qgym/utils/visualisation/typing.py
qgym/utils/visualisation/wrappers.py
qgym-0.3.1.dist-info/LICENSE
qgym-0.3.1.dist-info/METADATA
qgym-0.3.1.dist-info/WHEEL
qgym-0.3.1.dist-info/top_level.txt
qgym-0.3.1.dist-info/RECORD
