Metadata-Version: 2.1
Name: qgym
Version: 0.3.1
Summary: Reinforcement Learning Gym for Quantum Compilation
Author: QuTech (TNO, TU Delft)
Maintainer: QuTech (TNO, TU Delft)
License: 
Keywords: Reinforcement Learning,QuTech,TNO,TU Delft,Quantum,Gym,Quantum Compilation
Classifier: License :: OSI Approved :: Apache Software License
Classifier: Programming Language :: Python :: 3
Classifier: Programming Language :: Python :: 3.8
Classifier: Programming Language :: Python :: 3.9
Classifier: Programming Language :: Python :: 3.10
Classifier: Programming Language :: Python :: 3.11
Classifier: Programming Language :: Python :: 3.12
Classifier: Intended Audience :: Developers
Classifier: Intended Audience :: Information Technology
Classifier: Intended Audience :: Science/Research
Classifier: Topic :: Scientific/Engineering :: Artificial Intelligence
Classifier: Operating System :: OS Independent
Classifier: Typing :: Typed
Requires-Python: >=3.8
License-File: LICENSE
Requires-Dist: gymnasium >=0.28.1
Requires-Dist: networkx[default] >=2.6.3
Requires-Dist: numpy >=1.21.6
Requires-Dist: pygame
Provides-Extra: dev
Requires-Dist: black[jupyter] ; extra == 'dev'
Requires-Dist: isort ; extra == 'dev'
Requires-Dist: matplotlib ; extra == 'dev'
Requires-Dist: notebook ; extra == 'dev'
Requires-Dist: pytest ; extra == 'dev'
Requires-Dist: sphinx ; extra == 'dev'
Requires-Dist: sphinx-autodoc-typehints ; extra == 'dev'
Requires-Dist: sphinx-math-dollar ; extra == 'dev'
Requires-Dist: sphinx-rtd-theme ~=1.0 ; extra == 'dev'
Requires-Dist: stable-baselines3 >=2.0.0 ; extra == 'dev'
Requires-Dist: mypy ; extra == 'dev'
Requires-Dist: pylint ; extra == 'dev'
Requires-Dist: scipy >=1.7.3 ; extra == 'dev'
Provides-Extra: test
Requires-Dist: pytest ; extra == 'test'
Requires-Dist: stable-baselines3 >=2.0.0 ; extra == 'test'
Requires-Dist: scipy >=1.7.3 ; extra == 'test'
Provides-Extra: tutorial
Requires-Dist: matplotlib ; extra == 'tutorial'
Requires-Dist: notebook ; extra == 'tutorial'
Requires-Dist: stable-baselines3 >=2.0.0 ; extra == 'tutorial'
